globimap.cpython-38-i386-linux-gnu.so
helena-0.92.dist-info/WHEEL
helena-0.92.dist-info/LICENSE
helena-0.92.dist-info/METADATA
helena-0.92.dist-info/RECORD
helena-0.92.dist-info/top_level.txt
