Metadata-Version: 2.1
Name: helena
Version: 0.92
Summary: GloBiMap - A Probabilistic Data Structure for In-Memory Processing of Global Raster Datasets
Home-page: https://www.bgd.lrg.tum.de/en/
Author: Martin Werner and contributors
Author-email: martin.werner@tum.de
License: UNKNOWN
Project-URL: Source, https://github.com/mwernerds/globimap/
Project-URL: Tracker, https://github.com/mwernerds/globimap/issues
Platform: UNKNOWN
Classifier: Programming Language :: Python :: 3
Classifier: License :: OSI Approved :: MIT License
Classifier: Operating System :: Microsoft :: Windows
Classifier: Operating System :: POSIX
Classifier: Topic :: Database
Classifier: Topic :: Scientific/Engineering
Requires-Python: >=3.5
